{
  "project_info": {
    "project_number": "969352360034",
    "project_id": "guam-6b56b",
    "storage_bucket": "guam-6b56b.firebasestorage.app"
  },
  "client": [
    {
      "client_info": {
        "mobilesdk_app_id": "1:969352360034:android:3e85b6380e9fa83e4d613b",
        "android_client_info": {
          "package_name": "com.party.guam"
        }
      },
      "oauth_client": [],
      "api_key": [
        {
          "current_key": "AIzaSyD8AlqcsGP-cb10uJ3bV8bR1rrpwvPIqnQ"
        }
      ],
      "services": {
        "appinvite_service": {
          "other_platform_oauth_client": []
        }
      }
    }
  ],
  "configuration_version": "1"
}